reflex_resizable_panels/__init__.py
reflex_resizable_panels/resizable_panels.py
reflex_resizable_panels-0.0.1.dist-info/METADATA
reflex_resizable_panels-0.0.1.dist-info/WHEEL
reflex_resizable_panels-0.0.1.dist-info/top_level.txt
reflex_resizable_panels-0.0.1.dist-info/RECORD
