Metadata-Version: 2.1
Name: reflex-resizable-panels
Version: 0.0.1
Summary: A component for resizable panels
Author-email: Lendemor <contact@lendemor.dev>
License: Apache-2.0
Project-URL: Repository, https://github.com/Lendemor/reflex-resizable-panels
Project-URL: homepage, https://github.com/Lendemor/reflex-resizable-panels
Project-URL: source, https://github.com/Lendemor/reflex-resizable-panels
Keywords: reflex,reflex-custom-components
Classifier: Development Status :: 4 - Beta
Requires-Python: >=3.8
Requires-Dist: reflex >=0.5.0
Provides-Extra: dev
Requires-Dist: build ; extra == 'dev'
Requires-Dist: twine ; extra == 'dev'
